camel/__init__.py
camel/camel.py
camel_learn-1.1.2.dist-info/LICENSE
camel_learn-1.1.2.dist-info/METADATA
camel_learn-1.1.2.dist-info/WHEEL
camel_learn-1.1.2.dist-info/top_level.txt
camel_learn-1.1.2.dist-info/RECORD
