Metadata-Version: 2.1
Name: camel-learn
Version: 1.1.2
Summary: The official implementation for CAMEL: Curvature Augmented Manifold Embedding and Learning
Home-page: https://github.com/ymlasu/CAMEL
Author: Yongming Liu
Author-email: yongming.liu@asu.edu
Project-URL: Bug Tracker, https://github.com/ymlasu/CAMEL/issues
Keywords: CAMEL,dimension reduction,UMAP,tSNE,TriMap,PaCMAP,LargeVis,smallvis,manifold
Classifier: Programming Language :: Python :: 3
Classifier: License :: OSI Approved :: MIT License
Classifier: Operating System :: OS Independent
Classifier: Intended Audience :: Science/Research
Classifier: Intended Audience :: Developers
Requires-Python: >=3.9
License-File: LICENSE
Requires-Dist: scikit-learn >=1.3.0
Requires-Dist: numba >=0.59
Requires-Dist: annoy >=1.17
Requires-Dist: numpy >=1.24
